touchwoody/__init__.py
touchwoody/woody.py
touchwoody-0.1.1.dist-info/METADATA
touchwoody-0.1.1.dist-info/WHEEL
touchwoody-0.1.1.dist-info/entry_points.txt
touchwoody-0.1.1.dist-info/top_level.txt
touchwoody-0.1.1.dist-info/RECORD
